LICENSE
MANIFEST.in
README.md
setup.cfg
setup.py
data/GOES_EAST_IR.wld
data/GOES_EAST_VIS.wld
data/GOES_EAST_WV.wld
goesutils/__init__.py
goesutils/io.py
goesutils/plots.py
goesutils.egg-info/PKG-INFO
goesutils.egg-info/SOURCES.txt
goesutils.egg-info/dependency_links.txt
goesutils.egg-info/entry_points.txt
goesutils.egg-info/requires.txt
goesutils.egg-info/top_level.txt
tests/goes13-IR-2017-07-13-12.jpg
tests/test_all.py