Metadata-Version: 2.1
Name: goesutils
Version: 1.0.8
Summary: Simple download and plot GOES weather satellite data
Home-page: https://github.com/scivision/goesutils
Author: Michael Hirsch, Ph.D.
Author-email: scivision@users.noreply.github.com
License: UNKNOWN
Keywords: goes,satellite
Platform: UNKNOWN
Classifier: Development Status :: 4 - Beta
Classifier: Environment :: Console
Classifier: Intended Audience :: Science/Research
Classifier: Operating System :: OS Independent
Classifier: Programming Language :: Python :: 3.6
Classifier: Programming Language :: Python :: 3.7
Classifier: Topic :: Scientific/Engineering :: Atmospheric Science
Requires-Python: >= 3.6
Provides-Extra: tests
Provides-Extra: plots
Provides-Extra: cov
Provides-Extra: io
